pointwisepy/__init__.py
pointwisepy/convert.py
pointwisepy/create.py
pointwisepy/database.py
pointwisepy/defaults.py
pointwisepy/display.py
pointwisepy/examine.py
pointwisepy/extrude.py
pointwisepy/get.py
pointwisepy/grid.py
pointwisepy/transform.py
pointwisepy/utilities.py
pointwisepy-1.0.2.dist-info/METADATA
pointwisepy-1.0.2.dist-info/WHEEL
pointwisepy-1.0.2.dist-info/top_level.txt
pointwisepy-1.0.2.dist-info/RECORD
