Metadata-Version: 2.1
Name: pointwisepy
Version: 1.0.2
Project-URL: Homepage, https://github.com/bex-d/pointwisepy
Requires-Dist: pointwise-glyph-client
